{
    "tags": {
        "Formal": 0,
        "Casual": 1,
        "Party": 2,
        "Sporty": 3,
        "Seasonal": 4,
        "Vintage": 5,
        "Bohemian": 6,
        "Minimalist": 7,
        "Streetwear": 8,
        "Preppy": 9,
        "Oversized": 10,
        "Slim Fit": 11,
        "Straight Fit": 12,
        "A-Line": 13,
        "High-Waisted": 14,
        "Cropped": 15,
        "Denim": 16,
        "Linen": 17,
        "Silk": 18,
        "Knit": 19,
        "Leather": 20,
        "Words": 21,
        "Floral": 22,
        "Striped": 23,
        "Plaid": 24,
        "Geometric": 25,
        "Animal Print": 26,
        "Monochromatic": 27,
        "Camouflage": 28,
        "Pastel": 29,
        "Neutral": 30,
        "Bright": 31,
        "Sparkly": 32,
        "Metallic": 33,
        "Ethnic": 34,
        "Western": 35,
        "Asian-inspired": 36,
        "African-inspired": 37,
        "Classic": 38,
        "Unisex": 39,
        "Men": 40,
        "Women": 41,
        "Kids": 42,
        "Teen": 43,
        "Maternity": 44,
        "Bold": 45,
        "Romantic": 46,
        "Edgy": 47,
        "Comfortable": 48,
        "Low Heels": 49,
        "High Heels": 50,
        "No Sleeves": 51,
        "Short Sleeves": 52,
        "Long Sleeves": 53,
        "Buttoned": 54,
        "Zippered": 55,
        "Hooded": 56,
        "Collared": 57,
        "V-Neck": 58,
        "Crew Neck": 59,
        "Turtleneck": 60,
        "Scoop Neck": 61,
        "Boat": 62,
        "Plunging": 63,
        "Jewel": 64,
        "SweetHeart": 65,
        "Square": 66,
        "Surplice": 67,
        "Split": 68
    }
}